[
  {
    "id": "gdrmo-0001",
    "correctOption": "B",
    "difficulty": "medium",
    "sourceYear": 2024,
    "en": {
      "question": "If + means x, - means /, x means -, and / means +, then what is 12 + 4 - 2 x 6 / 8?",
      "options": [
        "24",
        "26",
        "28",
        "30"
      ],
      "explanation": "After substitution: 12 x 4 / 2 - 6 + 8. BODMAS: 12x4=48, 48/2=24, 24-6=18, 18+8=26."
    },
    "hi": {
      "question": "यदि + का अर्थ ×, - का अर्थ ÷, × का अर्थ -, और ÷ का अर्थ + है, तो 12 + 4 - 2 × 6 ÷ 8 का मान?",
      "options": [
        "24",
        "26",
        "28",
        "30"
      ],
      "explanation": "प्रतिस्थापन: 12×4÷2-6+8। BODMAS: 12×4=48, 48÷2=24, 24-6=18, 18+8=26।"
    }
  },
  {
    "id": "gdrmo-0002",
    "correctOption": "C",
    "difficulty": "easy",
    "sourceYear": 2023,
    "en": {
      "question": "If 16 * 4 = 64 and 25 * 3 = 75, then 18 * 5 = ?",
      "options": [
        "80",
        "85",
        "90",
        "95"
      ],
      "explanation": "The * operation means multiplication: 16x4=64, 25x3=75, 18x5=90."
    },
    "hi": {
      "question": "यदि 16 * 4 = 64 और 25 * 3 = 75, तो 18 * 5 = ?",
      "options": [
        "80",
        "85",
        "90",
        "95"
      ],
      "explanation": "* का अर्थ गुणा: 16×4=64, 25×3=75, 18×5=90।"
    }
  },
  {
    "id": "gdrmo-0003",
    "correctOption": "B",
    "difficulty": "medium",
    "sourceYear": 2024,
    "en": {
      "question": "If + means -, - means x, x means /, and / means +, then 15 + 3 - 2 x 6 / 2 = ?",
      "options": [
        "14",
        "16",
        "18",
        "20"
      ],
      "explanation": "After substitution: 15 - 3 x 2 / 6 + 2. BODMAS: 3x2=6, 6/6=1, 15-1+2=16."
    },
    "hi": {
      "question": "यदि + का अर्थ -, - का अर्थ ×, × का अर्थ ÷, ÷ का अर्थ +, तो 15 + 3 - 2 × 6 ÷ 2 = ?",
      "options": [
        "14",
        "16",
        "18",
        "20"
      ],
      "explanation": "प्रतिस्थापन: 15-3×2÷6+2। BODMAS: 3×2=6, 6÷6=1, 15-1+2=16।"
    }
  },
  {
    "id": "gdrmo-0004",
    "correctOption": "C",
    "difficulty": "easy",
    "sourceYear": 2023,
    "en": {
      "question": "If 8 * 3 = 24 and 7 * 5 = 35, then 9 * 6 = ?",
      "options": [
        "45",
        "48",
        "54",
        "56"
      ],
      "explanation": "The * operation means multiplication: 8x3=24, 7x5=35, 9x6=54."
    },
    "hi": {
      "question": "यदि 8 * 3 = 24 और 7 * 5 = 35, तो 9 * 6 = ?",
      "options": [
        "45",
        "48",
        "54",
        "56"
      ],
      "explanation": "* का अर्थ गुणा: 8×3=24, 7×5=35, 9×6=54।"
    }
  },
  {
    "id": "gdrmo-0005",
    "correctOption": "A",
    "difficulty": "medium",
    "sourceYear": 2024,
    "en": {
      "question": "If 5 # 3 = 16, 7 # 2 = 18, then 6 # 4 = ?",
      "options": [
        "20",
        "22",
        "24",
        "26"
      ],
      "explanation": "Pattern: a # b = (a + b) x 2. 5+3=8, 8x2=16. 7+2=9, 9x2=18. 6+4=10, 10x2=20."
    },
    "hi": {
      "question": "यदि 5 # 3 = 16, 7 # 2 = 18, तो 6 # 4 = ?",
      "options": [
        "20",
        "22",
        "24",
        "26"
      ],
      "explanation": "पैटर्न: a # b = (a+b)×2। 5+3=8, 8×2=16। 7+2=9, 9×2=18। 6+4=10, 10×2=20।"
    }
  },
  {
    "id": "gdrmo-0006",
    "correctOption": "C",
    "difficulty": "easy",
    "sourceYear": 2023,
    "en": {
      "question": "If 4 $ 2 = 8 and 5 $ 3 = 15, then 7 $ 4 = ?",
      "options": [
        "24",
        "26",
        "28",
        "30"
      ],
      "explanation": "Pattern: $ means multiplication. 4x2=8, 5x3=15, 7x4=28."
    },
    "hi": {
      "question": "यदि 4 $ 2 = 8 और 5 $ 3 = 15, तो 7 $ 4 = ?",
      "options": [
        "24",
        "26",
        "28",
        "30"
      ],
      "explanation": "$ का अर्थ गुणा: 4×2=8, 5×3=15, 7×4=28।"
    }
  },
  {
    "id": "gdrmo-0007",
    "correctOption": "C",
    "difficulty": "medium",
    "sourceYear": 2024,
    "en": {
      "question": "If P means +, Q means -, R means x, S means /, then 18 R 3 S 6 P 4 Q 2 = ?",
      "options": [
        "9",
        "10",
        "11",
        "12"
      ],
      "explanation": "18 x 3 / 6 + 4 - 2. BODMAS: 18x3=54, 54/6=9, 9+4=13, 13-2=11."
    },
    "hi": {
      "question": "यदि P का अर्थ +, Q का अर्थ -, R का अर्थ ×, S का अर्थ ÷, तो 18 R 3 S 6 P 4 Q 2 = ?",
      "options": [
        "9",
        "10",
        "11",
        "12"
      ],
      "explanation": "18×3÷6+4-2। BODMAS: 18×3=54, 54÷6=9, 9+4=13, 13-2=11।"
    }
  },
  {
    "id": "gdrmo-0008",
    "correctOption": "C",
    "difficulty": "medium",
    "sourceYear": 2023,
    "en": {
      "question": "If 3 @ 4 = 25 and 5 @ 6 = 61, then 2 @ 8 = ?",
      "options": [
        "64",
        "66",
        "68",
        "70"
      ],
      "explanation": "Pattern: a @ b = a^2 + b^2. 3^2+4^2=25. 5^2+6^2=61. 2^2+8^2=68."
    },
    "hi": {
      "question": "यदि 3 @ 4 = 25 और 5 @ 6 = 61, तो 2 @ 8 = ?",
      "options": [
        "64",
        "66",
        "68",
        "70"
      ],
      "explanation": "पैटर्न: a @ b = a^2 + b^2। 3^2+4^2=25। 5^2+6^2=61। 2^2+8^2=68।"
    }
  },
  {
    "id": "gdrmo-0009",
    "correctOption": "A",
    "difficulty": "medium",
    "sourceYear": 2025,
    "en": {
      "question": "What should replace '?' to make true: 6 ? 7 = 46 (using +, −, ×, or ÷)",
      "options": [
        "+",
        "÷",
        "×",
        "−"
      ],
      "explanation": "6 + 7 = 13. So '?' = +"
    },
    "hi": {
      "question": "'?' के स्थान पर क्या आएगा: 6 ? 7 = 46",
      "options": [
        "+",
        "÷",
        "×",
        "−"
      ],
      "explanation": "6 + 7 = 13। इसलिए '?' = +"
    }
  },
  {
    "id": "gdrmo-0010",
    "correctOption": "D",
    "difficulty": "medium",
    "sourceYear": 2025,
    "en": {
      "question": "If # means +, # means −, % means ×, * means ÷, evaluate: 10 % 5 * 4 = ?",
      "options": [
        "7.5",
        "21.5",
        "18.75",
        "12.5"
      ],
      "explanation": "10 × 5 ÷ 4 = 10 × 5 = 50, then 50 ÷ 4 = 12.5"
    },
    "hi": {
      "question": "If # means +, # means −, % means ×, * means ÷, evaluate: 10 % 5 * 4 = ?",
      "options": [
        "7.5",
        "21.5",
        "18.75",
        "12.5"
      ],
      "explanation": "10 × 5 ÷ 4 = 10 × 5 = 50, then 50 ÷ 4 = 12.5"
    }
  },
  {
    "id": "gdrmo-0011",
    "correctOption": "B",
    "difficulty": "medium",
    "sourceYear": 2025,
    "en": {
      "question": "If @ means +, $ means −, ∇ means ×, ⊗ means ÷, evaluate: 19 * 2 # 2 = ?",
      "options": [
        "34.5",
        "23",
        "22",
        "25"
      ],
      "explanation": "19 + 2 + 2 = 19 + 2 = 21, then 21 + 2 = 23"
    },
    "hi": {
      "question": "If @ means +, $ means −, ∇ means ×, ⊗ means ÷, evaluate: 19 * 2 # 2 = ?",
      "options": [
        "34.5",
        "23",
        "22",
        "25"
      ],
      "explanation": "19 + 2 + 2 = 19 + 2 = 21, then 21 + 2 = 23"
    }
  },
  {
    "id": "gdrmo-0012",
    "correctOption": "A",
    "difficulty": "medium",
    "sourceYear": 2025,
    "en": {
      "question": "What should replace '?' to make true: 9 ? 8 = 76 (using +, −, ×, or ÷)",
      "options": [
        "+",
        "÷",
        "−",
        "×"
      ],
      "explanation": "9 + 8 = 17. So '?' = +"
    },
    "hi": {
      "question": "'?' के स्थान पर क्या आएगा: 9 ? 8 = 76",
      "options": [
        "+",
        "÷",
        "−",
        "×"
      ],
      "explanation": "9 + 8 = 17। इसलिए '?' = +"
    }
  },
  {
    "id": "gdrmo-0013",
    "correctOption": "C",
    "difficulty": "medium",
    "sourceYear": 2025,
    "en": {
      "question": "If '+' and '−' are interchanged, evaluate: 26 + 14 − 3",
      "options": [
        "37",
        "43",
        "15",
        "9"
      ],
      "explanation": "After interchange: 26 − 14 + 3 = 26 - 14 + 3 = 15"
    },
    "hi": {
      "question": "यदि '+' और '−' को आपस में बदल दिया जाए, तो मान ज्ञात करें: 26 + 14 − 3",
      "options": [
        "37",
        "43",
        "15",
        "9"
      ],
      "explanation": "बदलने के बाद: 26 − 14 + 3 = 15"
    }
  },
  {
    "id": "gdrmo-0014",
    "correctOption": "C",
    "difficulty": "medium",
    "sourceYear": 2025,
    "en": {
      "question": "If '+' and '−' are interchanged, evaluate: 32 + 3 − 6",
      "options": [
        "23",
        "29",
        "35",
        "41"
      ],
      "explanation": "After interchange: 32 − 3 + 6 = 32 - 3 + 6 = 35"
    },
    "hi": {
      "question": "यदि '+' और '−' को आपस में बदल दिया जाए, तो मान ज्ञात करें: 32 + 3 − 6",
      "options": [
        "23",
        "29",
        "35",
        "41"
      ],
      "explanation": "बदलने के बाद: 32 − 3 + 6 = 35"
    }
  },
  {
    "id": "gdrmo-0015",
    "correctOption": "C",
    "difficulty": "medium",
    "sourceYear": 2025,
    "en": {
      "question": "If '+' and '−' are interchanged, evaluate: 19 + 10 − 6",
      "options": [
        "3",
        "23",
        "15",
        "35"
      ],
      "explanation": "After interchange: 19 − 10 + 6 = 19 - 10 + 6 = 15"
    },
    "hi": {
      "question": "यदि '+' और '−' को आपस में बदल दिया जाए, तो मान ज्ञात करें: 19 + 10 − 6",
      "options": [
        "3",
        "23",
        "15",
        "35"
      ],
      "explanation": "बदलने के बाद: 19 − 10 + 6 = 15"
    }
  },
  {
    "id": "gdrmo-0016",
    "correctOption": "C",
    "difficulty": "medium",
    "sourceYear": 2025,
    "en": {
      "question": "What should replace '?' to make true: 3 ? 3 = 14 (using +, −, ×, or ÷)",
      "options": [
        "−",
        "×",
        "+",
        "÷"
      ],
      "explanation": "3 + 3 = 6. So '?' = +"
    },
    "hi": {
      "question": "'?' के स्थान पर क्या आएगा: 3 ? 3 = 14",
      "options": [
        "−",
        "×",
        "+",
        "÷"
      ],
      "explanation": "3 + 3 = 6। इसलिए '?' = +"
    }
  },
  {
    "id": "gdrmo-0017",
    "correctOption": "C",
    "difficulty": "medium",
    "sourceYear": 2025,
    "en": {
      "question": "If @ means +, ⊗ means −, $ means ×, ⊕ means ÷, evaluate: 8 ⊗ 7 ⊗ 6 = ?",
      "options": [
        "-9",
        "3",
        "-5",
        "-7.5"
      ],
      "explanation": "8 − 7 − 6 = 8 − 7 = 1, then 1 − 6 = -5"
    },
    "hi": {
      "question": "If @ means +, ⊗ means −, $ means ×, ⊕ means ÷, evaluate: 8 ⊗ 7 ⊗ 6 = ?",
      "options": [
        "-9",
        "3",
        "-5",
        "-7.5"
      ],
      "explanation": "8 − 7 − 6 = 8 − 7 = 1, then 1 − 6 = -5"
    }
  },
  {
    "id": "gdrmo-0018",
    "correctOption": "B",
    "difficulty": "medium",
    "sourceYear": 2025,
    "en": {
      "question": "If Δ means +, # means −, @ means ×, $ means ÷, evaluate: 9 @ 11 @ 6 = ?",
      "options": [
        "891.0",
        "594",
        "593",
        "601"
      ],
      "explanation": "9 × 11 × 6 = 9 × 11 = 99, then 99 × 6 = 594"
    },
    "hi": {
      "question": "If Δ means +, # means −, @ means ×, $ means ÷, evaluate: 9 @ 11 @ 6 = ?",
      "options": [
        "891.0",
        "594",
        "593",
        "601"
      ],
      "explanation": "9 × 11 × 6 = 9 × 11 = 99, then 99 × 6 = 594"
    }
  },
  {
    "id": "gdrmo-0019",
    "correctOption": "B",
    "difficulty": "medium",
    "sourceYear": 2025,
    "en": {
      "question": "If '+' and '−' are interchanged, evaluate: 48 + 4 − 2",
      "options": [
        "50",
        "46",
        "54",
        "42"
      ],
      "explanation": "After interchange: 48 − 4 + 2 = 48 - 4 + 2 = 46"
    },
    "hi": {
      "question": "यदि '+' और '−' को आपस में बदल दिया जाए, तो मान ज्ञात करें: 48 + 4 − 2",
      "options": [
        "50",
        "46",
        "54",
        "42"
      ],
      "explanation": "बदलने के बाद: 48 − 4 + 2 = 46"
    }
  },
  {
    "id": "gdrmo-0020",
    "correctOption": "D",
    "difficulty": "medium",
    "sourceYear": 2025,
    "en": {
      "question": "What should replace '?' to make true: 8 ? 8 = 68 (using +, −, ×, or ÷)",
      "options": [
        "−",
        "÷",
        "×",
        "+"
      ],
      "explanation": "8 + 8 = 16. So '?' = +"
    },
    "hi": {
      "question": "'?' के स्थान पर क्या आएगा: 8 ? 8 = 68",
      "options": [
        "−",
        "÷",
        "×",
        "+"
      ],
      "explanation": "8 + 8 = 16। इसलिए '?' = +"
    }
  },
  {
    "id": "gdrmo-0021",
    "correctOption": "B",
    "difficulty": "medium",
    "sourceYear": 2025,
    "en": {
      "question": "If □ means +, ∇ means −, % means ×, % means ÷, evaluate: 4 □ 3 ∇ 4 = ?",
      "options": [
        "2",
        "3",
        "4.5",
        "11"
      ],
      "explanation": "4 + 3 − 4 = 4 + 3 = 7, then 7 − 4 = 3"
    },
    "hi": {
      "question": "If □ means +, ∇ means −, % means ×, % means ÷, evaluate: 4 □ 3 ∇ 4 = ?",
      "options": [
        "2",
        "3",
        "4.5",
        "11"
      ],
      "explanation": "4 + 3 − 4 = 4 + 3 = 7, then 7 − 4 = 3"
    }
  },
  {
    "id": "gdrmo-0022",
    "correctOption": "D",
    "difficulty": "medium",
    "sourceYear": 2025,
    "en": {
      "question": "If @ means +, # means −, % means ×, ⊗ means ÷, evaluate: 2 % 2 % 2 = ?",
      "options": [
        "12.0",
        "14",
        "6",
        "8"
      ],
      "explanation": "2 × 2 × 2 = 2 × 2 = 4, then 4 × 2 = 8"
    },
    "hi": {
      "question": "If @ means +, # means −, % means ×, ⊗ means ÷, evaluate: 2 % 2 % 2 = ?",
      "options": [
        "12.0",
        "14",
        "6",
        "8"
      ],
      "explanation": "2 × 2 × 2 = 2 × 2 = 4, then 4 × 2 = 8"
    }
  },
  {
    "id": "gdrmo-0023",
    "correctOption": "B",
    "difficulty": "medium",
    "sourceYear": 2025,
    "en": {
      "question": "If '+' and '−' are interchanged, evaluate: 12 + 12 − 5",
      "options": [
        "-5",
        "5",
        "29",
        "19"
      ],
      "explanation": "After interchange: 12 − 12 + 5 = 12 - 12 + 5 = 5"
    },
    "hi": {
      "question": "यदि '+' और '−' को आपस में बदल दिया जाए, तो मान ज्ञात करें: 12 + 12 − 5",
      "options": [
        "-5",
        "5",
        "29",
        "19"
      ],
      "explanation": "बदलने के बाद: 12 − 12 + 5 = 5"
    }
  },
  {
    "id": "gdrmo-0024",
    "correctOption": "C",
    "difficulty": "medium",
    "sourceYear": 2025,
    "en": {
      "question": "What should replace '?' to make true: 7 ? 4 = 32 (using +, −, ×, or ÷)",
      "options": [
        "×",
        "÷",
        "+",
        "−"
      ],
      "explanation": "7 + 4 = 11. So '?' = +"
    },
    "hi": {
      "question": "'?' के स्थान पर क्या आएगा: 7 ? 4 = 32",
      "options": [
        "×",
        "÷",
        "+",
        "−"
      ],
      "explanation": "7 + 4 = 11। इसलिए '?' = +"
    }
  },
  {
    "id": "gdrmo-0025",
    "correctOption": "D",
    "difficulty": "medium",
    "sourceYear": 2025,
    "en": {
      "question": "If '+' and '−' are interchanged, evaluate: 32 + 5 − 8",
      "options": [
        "29",
        "45",
        "19",
        "35"
      ],
      "explanation": "After interchange: 32 − 5 + 8 = 32 - 5 + 8 = 35"
    },
    "hi": {
      "question": "यदि '+' और '−' को आपस में बदल दिया जाए, तो मान ज्ञात करें: 32 + 5 − 8",
      "options": [
        "29",
        "45",
        "19",
        "35"
      ],
      "explanation": "बदलने के बाद: 32 − 5 + 8 = 35"
    }
  },
  {
    "id": "gdrmo-0026",
    "correctOption": "B",
    "difficulty": "medium",
    "sourceYear": 2025,
    "en": {
      "question": "If '+' and '−' are interchanged, evaluate: 15 + 11 − 3",
      "options": [
        "23",
        "7",
        "29",
        "1"
      ],
      "explanation": "After interchange: 15 − 11 + 3 = 15 - 11 + 3 = 7"
    },
    "hi": {
      "question": "यदि '+' और '−' को आपस में बदल दिया जाए, तो मान ज्ञात करें: 15 + 11 − 3",
      "options": [
        "23",
        "7",
        "29",
        "1"
      ],
      "explanation": "बदलने के बाद: 15 − 11 + 3 = 7"
    }
  },
  {
    "id": "gdrmo-0027",
    "correctOption": "A",
    "difficulty": "medium",
    "sourceYear": 2025,
    "en": {
      "question": "If '+' and '−' are interchanged, evaluate: 31 + 10 − 8",
      "options": [
        "29",
        "33",
        "13",
        "49"
      ],
      "explanation": "After interchange: 31 − 10 + 8 = 31 - 10 + 8 = 29"
    },
    "hi": {
      "question": "यदि '+' और '−' को आपस में बदल दिया जाए, तो मान ज्ञात करें: 31 + 10 − 8",
      "options": [
        "29",
        "33",
        "13",
        "49"
      ],
      "explanation": "बदलने के बाद: 31 − 10 + 8 = 29"
    }
  },
  {
    "id": "gdrmo-0028",
    "correctOption": "B",
    "difficulty": "medium",
    "sourceYear": 2025,
    "en": {
      "question": "If ∇ means +, □ means −, ⊕ means ×, % means ÷, evaluate: 11 □ 7 # 4 = ?",
      "options": [
        "7.0",
        "1",
        "-1.0",
        "1.5"
      ],
      "explanation": "11 − 7 ÷ 4 = 11 − 7 = 4, then 4 ÷ 4 = 1.0"
    },
    "hi": {
      "question": "If ∇ means +, □ means −, ⊕ means ×, % means ÷, evaluate: 11 □ 7 # 4 = ?",
      "options": [
        "7.0",
        "1",
        "-1.0",
        "1.5"
      ],
      "explanation": "11 − 7 ÷ 4 = 11 − 7 = 4, then 4 ÷ 4 = 1.0"
    }
  },
  {
    "id": "gdrmo-0029",
    "correctOption": "A",
    "difficulty": "medium",
    "sourceYear": 2025,
    "en": {
      "question": "What should replace '?' to make true: 2 ? 2 = 8 (using +, −, ×, or ÷)",
      "options": [
        "+",
        "−",
        "×",
        "÷"
      ],
      "explanation": "2 + 2 = 4. So '?' = +"
    },
    "hi": {
      "question": "'?' के स्थान पर क्या आएगा: 2 ? 2 = 8",
      "options": [
        "+",
        "−",
        "×",
        "÷"
      ],
      "explanation": "2 + 2 = 4। इसलिए '?' = +"
    }
  },
  {
    "id": "gdrmo-0030",
    "correctOption": "D",
    "difficulty": "medium",
    "sourceYear": 2025,
    "en": {
      "question": "If '+' and '−' are interchanged, evaluate: 41 + 11 − 8",
      "options": [
        "60",
        "22",
        "44",
        "38"
      ],
      "explanation": "After interchange: 41 − 11 + 8 = 41 - 11 + 8 = 38"
    },
    "hi": {
      "question": "यदि '+' और '−' को आपस में बदल दिया जाए, तो मान ज्ञात करें: 41 + 11 − 8",
      "options": [
        "60",
        "22",
        "44",
        "38"
      ],
      "explanation": "बदलने के बाद: 41 − 11 + 8 = 38"
    }
  },
  {
    "id": "gdrmo-0031",
    "correctOption": "C",
    "difficulty": "medium",
    "sourceYear": 2025,
    "en": {
      "question": "If @ means +, % means −, # means ×, % means ÷, evaluate: 15 % 12 % 6 = ?",
      "options": [
        "-4.5",
        "3",
        "-3",
        "-6"
      ],
      "explanation": "15 − 12 − 6 = 15 − 12 = 3, then 3 − 6 = -3"
    },
    "hi": {
      "question": "If @ means +, % means −, # means ×, % means ÷, evaluate: 15 % 12 % 6 = ?",
      "options": [
        "-4.5",
        "3",
        "-3",
        "-6"
      ],
      "explanation": "15 − 12 − 6 = 15 − 12 = 3, then 3 − 6 = -3"
    }
  },
  {
    "id": "gdrmo-0032",
    "correctOption": "D",
    "difficulty": "medium",
    "sourceYear": 2025,
    "en": {
      "question": "If # means +, ∇ means −, Δ means ×, @ means ÷, evaluate: 15 @ 2 @ 5 = ?",
      "options": [
        "11.5",
        "2.25",
        "0.5",
        "1.5"
      ],
      "explanation": "15 ÷ 2 ÷ 5 = 15 ÷ 2 = 7.5, then 7.5 ÷ 5 = 1.5"
    },
    "hi": {
      "question": "If # means +, ∇ means −, Δ means ×, @ means ÷, evaluate: 15 @ 2 @ 5 = ?",
      "options": [
        "11.5",
        "2.25",
        "0.5",
        "1.5"
      ],
      "explanation": "15 ÷ 2 ÷ 5 = 15 ÷ 2 = 7.5, then 7.5 ÷ 5 = 1.5"
    }
  },
  {
    "id": "gdrmo-0033",
    "correctOption": "D",
    "difficulty": "medium",
    "sourceYear": 2025,
    "en": {
      "question": "If ∇ means +, * means −, $ means ×, ⊗ means ÷, evaluate: 3 * 3 $ 7 = ?",
      "options": [
        "-5",
        "6",
        "0.0",
        "0"
      ],
      "explanation": "3 − 3 × 7 = 3 − 3 = 0, then 0 × 7 = 0"
    },
    "hi": {
      "question": "If ∇ means +, * means −, $ means ×, ⊗ means ÷, evaluate: 3 * 3 $ 7 = ?",
      "options": [
        "-5",
        "6",
        "0.0",
        "0"
      ],
      "explanation": "3 − 3 × 7 = 3 − 3 = 0, then 0 × 7 = 0"
    }
  },
  {
    "id": "gdrmo-0034",
    "correctOption": "A",
    "difficulty": "medium",
    "sourceYear": 2025,
    "en": {
      "question": "If @ means +, # means −, @ means ×, * means ÷, evaluate: 6 * 12 * 3 = ?",
      "options": [
        "0.17",
        "-1.83",
        "0.26",
        "9.17"
      ],
      "explanation": "6 ÷ 12 ÷ 3 = 6 ÷ 12 = 0.5, then 0.5 ÷ 3 = 0.17"
    },
    "hi": {
      "question": "If @ means +, # means −, @ means ×, * means ÷, evaluate: 6 * 12 * 3 = ?",
      "options": [
        "0.17",
        "-1.83",
        "0.26",
        "9.17"
      ],
      "explanation": "6 ÷ 12 ÷ 3 = 6 ÷ 12 = 0.5, then 0.5 ÷ 3 = 0.17"
    }
  },
  {
    "id": "gdrmo-0035",
    "correctOption": "C",
    "difficulty": "medium",
    "sourceYear": 2025,
    "en": {
      "question": "If Δ means +, # means −, ⊕ means ×, $ means ÷, evaluate: 20 ⊕ 9 Δ 9 = ?",
      "options": [
        "194",
        "185",
        "189",
        "283.5"
      ],
      "explanation": "20 × 9 + 9 = 20 × 9 = 180, then 180 + 9 = 189"
    },
    "hi": {
      "question": "If Δ means +, # means −, ⊕ means ×, $ means ÷, evaluate: 20 ⊕ 9 Δ 9 = ?",
      "options": [
        "194",
        "185",
        "189",
        "283.5"
      ],
      "explanation": "20 × 9 + 9 = 20 × 9 = 180, then 180 + 9 = 189"
    }
  },
  {
    "id": "gdrmo-0036",
    "correctOption": "B",
    "difficulty": "medium",
    "sourceYear": 2025,
    "en": {
      "question": "What should replace '?' to make true: 5 ? 8 = 44 (using +, −, ×, or ÷)",
      "options": [
        "÷",
        "+",
        "×",
        "−"
      ],
      "explanation": "5 + 8 = 13. So '?' = +"
    },
    "hi": {
      "question": "'?' के स्थान पर क्या आएगा: 5 ? 8 = 44",
      "options": [
        "÷",
        "+",
        "×",
        "−"
      ],
      "explanation": "5 + 8 = 13। इसलिए '?' = +"
    }
  },
  {
    "id": "gdrmo-0037",
    "correctOption": "C",
    "difficulty": "medium",
    "sourceYear": 2025,
    "en": {
      "question": "If $ means +, # means −, @ means ×, □ means ÷, evaluate: 8 □ 13 □ 10 = ?",
      "options": [
        "-1.94",
        "0.09",
        "0.06",
        "10.06"
      ],
      "explanation": "8 ÷ 13 ÷ 10 = 8 ÷ 13 = 0.6153846153846154, then 0.6153846153846154 ÷ 10 = 0.06"
    },
    "hi": {
      "question": "If $ means +, # means −, @ means ×, □ means ÷, evaluate: 8 □ 13 □ 10 = ?",
      "options": [
        "-1.94",
        "0.09",
        "0.06",
        "10.06"
      ],
      "explanation": "8 ÷ 13 ÷ 10 = 8 ÷ 13 = 0.6153846153846154, then 0.6153846153846154 ÷ 10 = 0.06"
    }
  },
  {
    "id": "gdrmo-0038",
    "correctOption": "C",
    "difficulty": "medium",
    "sourceYear": 2025,
    "en": {
      "question": "If '+' and '−' are interchanged, evaluate: 33 + 10 − 7",
      "options": [
        "50",
        "16",
        "30",
        "36"
      ],
      "explanation": "After interchange: 33 − 10 + 7 = 33 - 10 + 7 = 30"
    },
    "hi": {
      "question": "यदि '+' और '−' को आपस में बदल दिया जाए, तो मान ज्ञात करें: 33 + 10 − 7",
      "options": [
        "50",
        "16",
        "30",
        "36"
      ],
      "explanation": "बदलने के बाद: 33 − 10 + 7 = 30"
    }
  },
  {
    "id": "gdrmo-0039",
    "correctOption": "B",
    "difficulty": "medium",
    "sourceYear": 2025,
    "en": {
      "question": "What should replace '?' to make true: 9 ? 6 = 58 (using +, −, ×, or ÷)",
      "options": [
        "×",
        "+",
        "÷",
        "−"
      ],
      "explanation": "9 + 6 = 15. So '?' = +"
    },
    "hi": {
      "question": "'?' के स्थान पर क्या आएगा: 9 ? 6 = 58",
      "options": [
        "×",
        "+",
        "÷",
        "−"
      ],
      "explanation": "9 + 6 = 15। इसलिए '?' = +"
    }
  },
  {
    "id": "gdrmo-0040",
    "correctOption": "D",
    "difficulty": "medium",
    "sourceYear": 2025,
    "en": {
      "question": "If $ means +, # means −, $ means ×, ⊕ means ÷, evaluate: 7 * 15 ⊕ 6 = ?",
      "options": [
        "-4.33",
        "-2.0",
        "5.67",
        "-1.33"
      ],
      "explanation": "7 − 15 ÷ 6 = 7 − 15 = -8, then -8 ÷ 6 = -1.33"
    },
    "hi": {
      "question": "If $ means +, # means −, $ means ×, ⊕ means ÷, evaluate: 7 * 15 ⊕ 6 = ?",
      "options": [
        "-4.33",
        "-2.0",
        "5.67",
        "-1.33"
      ],
      "explanation": "7 − 15 ÷ 6 = 7 − 15 = -8, then -8 ÷ 6 = -1.33"
    }
  },
  {
    "id": "gdrmo-0041",
    "correctOption": "B",
    "difficulty": "medium",
    "sourceYear": 2025,
    "en": {
      "question": "If '+' and '−' are interchanged, evaluate: 24 + 7 − 7",
      "options": [
        "38",
        "24",
        "10",
        "24"
      ],
      "explanation": "After interchange: 24 − 7 + 7 = 24 - 7 + 7 = 24"
    },
    "hi": {
      "question": "यदि '+' और '−' को आपस में बदल दिया जाए, तो मान ज्ञात करें: 24 + 7 − 7",
      "options": [
        "38",
        "24",
        "10",
        "24"
      ],
      "explanation": "बदलने के बाद: 24 − 7 + 7 = 24"
    }
  },
  {
    "id": "gdrmo-0042",
    "correctOption": "C",
    "difficulty": "medium",
    "sourceYear": 2025,
    "en": {
      "question": "If @ means +, # means −, □ means ×, Δ means ÷, evaluate: 13 * 7 Δ 3 = ?",
      "options": [
        "5.67",
        "10.0",
        "6.67",
        "7.67"
      ],
      "explanation": "13 + 7 ÷ 3 = 13 + 7 = 20, then 20 ÷ 3 = 6.67"
    },
    "hi": {
      "question": "If @ means +, # means −, □ means ×, Δ means ÷, evaluate: 13 * 7 Δ 3 = ?",
      "options": [
        "5.67",
        "10.0",
        "6.67",
        "7.67"
      ],
      "explanation": "13 + 7 ÷ 3 = 13 + 7 = 20, then 20 ÷ 3 = 6.67"
    }
  },
  {
    "id": "gdrmo-0043",
    "correctOption": "C",
    "difficulty": "medium",
    "sourceYear": 2025,
    "en": {
      "question": "What should replace '?' to make true: 3 ? 2 = 8 (using +, −, ×, or ÷)",
      "options": [
        "×",
        "−",
        "+",
        "÷"
      ],
      "explanation": "3 + 2 = 5. So '?' = +"
    },
    "hi": {
      "question": "'?' के स्थान पर क्या आएगा: 3 ? 2 = 8",
      "options": [
        "×",
        "−",
        "+",
        "÷"
      ],
      "explanation": "3 + 2 = 5। इसलिए '?' = +"
    }
  },
  {
    "id": "gdrmo-0044",
    "correctOption": "A",
    "difficulty": "medium",
    "sourceYear": 2025,
    "en": {
      "question": "If # means +, # means −, $ means ×, % means ÷, evaluate: 13 * 5 % 6 = ?",
      "options": [
        "10.83",
        "16.25",
        "12.83",
        "5.83"
      ],
      "explanation": "13 × 5 ÷ 6 = 13 × 5 = 65, then 65 ÷ 6 = 10.83"
    },
    "hi": {
      "question": "If # means +, # means −, $ means ×, % means ÷, evaluate: 13 * 5 % 6 = ?",
      "options": [
        "10.83",
        "16.25",
        "12.83",
        "5.83"
      ],
      "explanation": "13 × 5 ÷ 6 = 13 × 5 = 65, then 65 ÷ 6 = 10.83"
    }
  },
  {
    "id": "gdrmo-0045",
    "correctOption": "B",
    "difficulty": "medium",
    "sourceYear": 2025,
    "en": {
      "question": "If # means +, @ means −, ⊗ means ×, % means ÷, evaluate: 20 @ 9 # 5 = ?",
      "options": [
        "25",
        "16",
        "24.0",
        "13"
      ],
      "explanation": "20 − 9 + 5 = 20 − 9 = 11, then 11 + 5 = 16"
    },
    "hi": {
      "question": "If # means +, @ means −, ⊗ means ×, % means ÷, evaluate: 20 @ 9 # 5 = ?",
      "options": [
        "25",
        "16",
        "24.0",
        "13"
      ],
      "explanation": "20 − 9 + 5 = 20 − 9 = 11, then 11 + 5 = 16"
    }
  },
  {
    "id": "gdrmo-0046",
    "correctOption": "A",
    "difficulty": "medium",
    "sourceYear": 2025,
    "en": {
      "question": "If $ means +, % means −, # means ×, % means ÷, evaluate: 8 * 3 % 6 = ?",
      "options": [
        "-3.33",
        "0.6699999999999999",
        "-5.0",
        "-4.33"
      ],
      "explanation": "8 ÷ 3 − 6 = 8 ÷ 3 = 2.6666666666666665, then 2.6666666666666665 − 6 = -3.33"
    },
    "hi": {
      "question": "If $ means +, % means −, # means ×, % means ÷, evaluate: 8 * 3 % 6 = ?",
      "options": [
        "-3.33",
        "0.6699999999999999",
        "-5.0",
        "-4.33"
      ],
      "explanation": "8 ÷ 3 − 6 = 8 ÷ 3 = 2.6666666666666665, then 2.6666666666666665 − 6 = -3.33"
    }
  },
  {
    "id": "gdrmo-0047",
    "correctOption": "A",
    "difficulty": "medium",
    "sourceYear": 2025,
    "en": {
      "question": "If '+' and '−' are interchanged, evaluate: 26 + 14 − 2",
      "options": [
        "14",
        "38",
        "10",
        "42"
      ],
      "explanation": "After interchange: 26 − 14 + 2 = 26 - 14 + 2 = 14"
    },
    "hi": {
      "question": "यदि '+' और '−' को आपस में बदल दिया जाए, तो मान ज्ञात करें: 26 + 14 − 2",
      "options": [
        "14",
        "38",
        "10",
        "42"
      ],
      "explanation": "बदलने के बाद: 26 − 14 + 2 = 14"
    }
  },
  {
    "id": "gdrmo-0048",
    "correctOption": "D",
    "difficulty": "medium",
    "sourceYear": 2025,
    "en": {
      "question": "If ⊗ means +, ⊕ means −, $ means ×, % means ÷, evaluate: 16 * 5 ⊕ 6 = ?",
      "options": [
        "111.0",
        "69",
        "75",
        "74"
      ],
      "explanation": "16 × 5 − 6 = 16 × 5 = 80, then 80 − 6 = 74"
    },
    "hi": {
      "question": "If ⊗ means +, ⊕ means −, $ means ×, % means ÷, evaluate: 16 * 5 ⊕ 6 = ?",
      "options": [
        "111.0",
        "69",
        "75",
        "74"
      ],
      "explanation": "16 × 5 − 6 = 16 × 5 = 80, then 80 − 6 = 74"
    }
  },
  {
    "id": "gdrmo-0049",
    "correctOption": "C",
    "difficulty": "medium",
    "sourceYear": 2025,
    "en": {
      "question": "If ∇ means +, @ means −, Δ means ×, * means ÷, evaluate: 7 @ 7 * 10 = ?",
      "options": [
        "2.0",
        "0.0",
        "0",
        "-4.0"
      ],
      "explanation": "7 − 7 ÷ 10 = 7 − 7 = 0, then 0 ÷ 10 = 0.0"
    },
    "hi": {
      "question": "If ∇ means +, @ means −, Δ means ×, * means ÷, evaluate: 7 @ 7 * 10 = ?",
      "options": [
        "2.0",
        "0.0",
        "0",
        "-4.0"
      ],
      "explanation": "7 − 7 ÷ 10 = 7 − 7 = 0, then 0 ÷ 10 = 0.0"
    }
  },
  {
    "id": "gdrmo-0050",
    "correctOption": "D",
    "difficulty": "medium",
    "sourceYear": 2025,
    "en": {
      "question": "If ∇ means +, # means −, * means ×, ⊗ means ÷, evaluate: 15 * 15 ∇ 2 = ?",
      "options": [
        "3.0",
        "1",
        "11",
        "2"
      ],
      "explanation": "15 − 15 + 2 = 15 − 15 = 0, then 0 + 2 = 2"
    },
    "hi": {
      "question": "If ∇ means +, # means −, * means ×, ⊗ means ÷, evaluate: 15 * 15 ∇ 2 = ?",
      "options": [
        "3.0",
        "1",
        "11",
        "2"
      ],
      "explanation": "15 − 15 + 2 = 15 − 15 = 0, then 0 + 2 = 2"
    }
  },
  {
    "id": "gdrmo-0051",
    "correctOption": "A",
    "difficulty": "medium",
    "sourceYear": 2025,
    "en": {
      "question": "If '+' and '−' are interchanged, evaluate: 22 + 12 − 5",
      "options": [
        "15",
        "5",
        "39",
        "29"
      ],
      "explanation": "After interchange: 22 − 12 + 5 = 22 - 12 + 5 = 15"
    },
    "hi": {
      "question": "यदि '+' और '−' को आपस में बदल दिया जाए, तो मान ज्ञात करें: 22 + 12 − 5",
      "options": [
        "15",
        "5",
        "39",
        "29"
      ],
      "explanation": "बदलने के बाद: 22 − 12 + 5 = 15"
    }
  },
  {
    "id": "gdrmo-0052",
    "correctOption": "C",
    "difficulty": "medium",
    "sourceYear": 2025,
    "en": {
      "question": "If □ means +, # means −, $ means ×, % means ÷, evaluate: 3 # 10 # 7 = ?",
      "options": [
        "-11",
        "-18",
        "-14",
        "-21.0"
      ],
      "explanation": "3 − 10 − 7 = 3 − 10 = -7, then -7 − 7 = -14"
    },
    "hi": {
      "question": "If □ means +, # means −, $ means ×, % means ÷, evaluate: 3 # 10 # 7 = ?",
      "options": [
        "-11",
        "-18",
        "-14",
        "-21.0"
      ],
      "explanation": "3 − 10 − 7 = 3 − 10 = -7, then -7 − 7 = -14"
    }
  },
  {
    "id": "gdrmo-0053",
    "correctOption": "A",
    "difficulty": "medium",
    "sourceYear": 2025,
    "en": {
      "question": "What should replace '?' to make true: 9 ? 5 = 49 (using +, −, ×, or ÷)",
      "options": [
        "+",
        "×",
        "−",
        "÷"
      ],
      "explanation": "9 + 5 = 14. So '?' = +"
    },
    "hi": {
      "question": "'?' के स्थान पर क्या आएगा: 9 ? 5 = 49",
      "options": [
        "+",
        "×",
        "−",
        "÷"
      ],
      "explanation": "9 + 5 = 14। इसलिए '?' = +"
    }
  },
  {
    "id": "gdrmo-0054",
    "correctOption": "D",
    "difficulty": "medium",
    "sourceYear": 2025,
    "en": {
      "question": "If □ means +, % means −, Δ means ×, # means ÷, evaluate: 10 # 6 # 5 = ?",
      "options": [
        "-0.6699999999999999",
        "0.49",
        "5.33",
        "0.33"
      ],
      "explanation": "10 ÷ 6 ÷ 5 = 10 ÷ 6 = 1.6666666666666667, then 1.6666666666666667 ÷ 5 = 0.33"
    },
    "hi": {
      "question": "If □ means +, % means −, Δ means ×, # means ÷, evaluate: 10 # 6 # 5 = ?",
      "options": [
        "-0.6699999999999999",
        "0.49",
        "5.33",
        "0.33"
      ],
      "explanation": "10 ÷ 6 ÷ 5 = 10 ÷ 6 = 1.6666666666666667, then 1.6666666666666667 ÷ 5 = 0.33"
    }
  },
  {
    "id": "gdrmo-0055",
    "correctOption": "D",
    "difficulty": "medium",
    "sourceYear": 2025,
    "en": {
      "question": "If '+' and '−' are interchanged, evaluate: 48 + 11 − 5",
      "options": [
        "32",
        "64",
        "54",
        "42"
      ],
      "explanation": "After interchange: 48 − 11 + 5 = 48 - 11 + 5 = 42"
    },
    "hi": {
      "question": "यदि '+' और '−' को आपस में बदल दिया जाए, तो मान ज्ञात करें: 48 + 11 − 5",
      "options": [
        "32",
        "64",
        "54",
        "42"
      ],
      "explanation": "बदलने के बाद: 48 − 11 + 5 = 42"
    }
  },
  {
    "id": "gdrmo-0056",
    "correctOption": "D",
    "difficulty": "medium",
    "sourceYear": 2025,
    "en": {
      "question": "If '+' and '−' are interchanged, evaluate: 36 + 7 − 4",
      "options": [
        "47",
        "25",
        "39",
        "33"
      ],
      "explanation": "After interchange: 36 − 7 + 4 = 36 - 7 + 4 = 33"
    },
    "hi": {
      "question": "यदि '+' और '−' को आपस में बदल दिया जाए, तो मान ज्ञात करें: 36 + 7 − 4",
      "options": [
        "47",
        "25",
        "39",
        "33"
      ],
      "explanation": "बदलने के बाद: 36 − 7 + 4 = 33"
    }
  },
  {
    "id": "gdrmo-0057",
    "correctOption": "A",
    "difficulty": "medium",
    "sourceYear": 2025,
    "en": {
      "question": "If '+' and '−' are interchanged, evaluate: 23 + 4 − 3",
      "options": [
        "22",
        "16",
        "30",
        "24"
      ],
      "explanation": "After interchange: 23 − 4 + 3 = 23 - 4 + 3 = 22"
    },
    "hi": {
      "question": "यदि '+' और '−' को आपस में बदल दिया जाए, तो मान ज्ञात करें: 23 + 4 − 3",
      "options": [
        "22",
        "16",
        "30",
        "24"
      ],
      "explanation": "बदलने के बाद: 23 − 4 + 3 = 22"
    }
  },
  {
    "id": "gdrmo-0058",
    "correctOption": "A",
    "difficulty": "medium",
    "sourceYear": 2025,
    "en": {
      "question": "If '+' and '−' are interchanged, evaluate: 15 + 5 − 7",
      "options": [
        "17",
        "27",
        "3",
        "13"
      ],
      "explanation": "After interchange: 15 − 5 + 7 = 15 - 5 + 7 = 17"
    },
    "hi": {
      "question": "यदि '+' और '−' को आपस में बदल दिया जाए, तो मान ज्ञात करें: 15 + 5 − 7",
      "options": [
        "17",
        "27",
        "3",
        "13"
      ],
      "explanation": "बदलने के बाद: 15 − 5 + 7 = 17"
    }
  },
  {
    "id": "gdrmo-0059",
    "correctOption": "D",
    "difficulty": "medium",
    "sourceYear": 2025,
    "en": {
      "question": "If # means +, # means −, $ means ×, ∇ means ÷, evaluate: 3 ∇ 15 # 2 = ?",
      "options": [
        "-0.7999999999999998",
        "3.3",
        "9.2",
        "2.2"
      ],
      "explanation": "3 ÷ 15 + 2 = 3 ÷ 15 = 0.2, then 0.2 + 2 = 2.2"
    },
    "hi": {
      "question": "If # means +, # means −, $ means ×, ∇ means ÷, evaluate: 3 ∇ 15 # 2 = ?",
      "options": [
        "-0.7999999999999998",
        "3.3",
        "9.2",
        "2.2"
      ],
      "explanation": "3 ÷ 15 + 2 = 3 ÷ 15 = 0.2, then 0.2 + 2 = 2.2"
    }
  },
  {
    "id": "gdrmo-0060",
    "correctOption": "D",
    "difficulty": "medium",
    "sourceYear": 2025,
    "en": {
      "question": "If $ means +, ∇ means −, Δ means ×, * means ÷, evaluate: 7 * 7 ∇ 4 = ?",
      "options": [
        "6.0",
        "-4.5",
        "-5.0",
        "-3"
      ],
      "explanation": "7 ÷ 7 − 4 = 7 ÷ 7 = 1.0, then 1.0 − 4 = -3.0"
    },
    "hi": {
      "question": "If $ means +, ∇ means −, Δ means ×, * means ÷, evaluate: 7 * 7 ∇ 4 = ?",
      "options": [
        "6.0",
        "-4.5",
        "-5.0",
        "-3"
      ],
      "explanation": "7 ÷ 7 − 4 = 7 ÷ 7 = 1.0, then 1.0 − 4 = -3.0"
    }
  },
  {
    "id": "gdrmo-0061",
    "correctOption": "B",
    "difficulty": "medium",
    "sourceYear": 2025,
    "en": {
      "question": "If '+' and '−' are interchanged, evaluate: 23 + 3 − 7",
      "options": [
        "19",
        "27",
        "33",
        "13"
      ],
      "explanation": "After interchange: 23 − 3 + 7 = 23 - 3 + 7 = 27"
    },
    "hi": {
      "question": "यदि '+' और '−' को आपस में बदल दिया जाए, तो मान ज्ञात करें: 23 + 3 − 7",
      "options": [
        "19",
        "27",
        "33",
        "13"
      ],
      "explanation": "बदलने के बाद: 23 − 3 + 7 = 27"
    }
  },
  {
    "id": "gdrmo-0062",
    "correctOption": "A",
    "difficulty": "medium",
    "sourceYear": 2025,
    "en": {
      "question": "If '+' and '−' are interchanged, evaluate: 27 + 3 − 5",
      "options": [
        "29",
        "25",
        "19",
        "35"
      ],
      "explanation": "After interchange: 27 − 3 + 5 = 27 - 3 + 5 = 29"
    },
    "hi": {
      "question": "यदि '+' और '−' को आपस में बदल दिया जाए, तो मान ज्ञात करें: 27 + 3 − 5",
      "options": [
        "29",
        "25",
        "19",
        "35"
      ],
      "explanation": "बदलने के बाद: 27 − 3 + 5 = 29"
    }
  },
  {
    "id": "gdrmo-0063",
    "correctOption": "D",
    "difficulty": "medium",
    "sourceYear": 2025,
    "en": {
      "question": "If '+' and '−' are interchanged, evaluate: 20 + 15 − 4",
      "options": [
        "39",
        "1",
        "31",
        "9"
      ],
      "explanation": "After interchange: 20 − 15 + 4 = 20 - 15 + 4 = 9"
    },
    "hi": {
      "question": "यदि '+' और '−' को आपस में बदल दिया जाए, तो मान ज्ञात करें: 20 + 15 − 4",
      "options": [
        "39",
        "1",
        "31",
        "9"
      ],
      "explanation": "बदलने के बाद: 20 − 15 + 4 = 9"
    }
  },
  {
    "id": "gdrmo-0064",
    "correctOption": "B",
    "difficulty": "medium",
    "sourceYear": 2025,
    "en": {
      "question": "If @ means +, ⊗ means −, * means ×, $ means ÷, evaluate: 4 @ 14 $ 6 = ?",
      "options": [
        "11.0",
        "3",
        "0.0",
        "4.5"
      ],
      "explanation": "4 + 14 ÷ 6 = 4 + 14 = 18, then 18 ÷ 6 = 3.0"
    },
    "hi": {
      "question": "If @ means +, ⊗ means −, * means ×, $ means ÷, evaluate: 4 @ 14 $ 6 = ?",
      "options": [
        "11.0",
        "3",
        "0.0",
        "4.5"
      ],
      "explanation": "4 + 14 ÷ 6 = 4 + 14 = 18, then 18 ÷ 6 = 3.0"
    }
  },
  {
    "id": "gdrmo-0065",
    "correctOption": "B",
    "difficulty": "medium",
    "sourceYear": 2025,
    "en": {
      "question": "If # means +, Δ means −, $ means ×, ⊕ means ÷, evaluate: 13 ⊕ 5 # 4 = ?",
      "options": [
        "15.6",
        "10.4",
        "8.4",
        "19.4"
      ],
      "explanation": "13 ÷ 5 × 4 = 13 ÷ 5 = 2.6, then 2.6 × 4 = 10.4"
    },
    "hi": {
      "question": "If # means +, Δ means −, $ means ×, ⊕ means ÷, evaluate: 13 ⊕ 5 # 4 = ?",
      "options": [
        "15.6",
        "10.4",
        "8.4",
        "19.4"
      ],
      "explanation": "13 ÷ 5 × 4 = 13 ÷ 5 = 2.6, then 2.6 × 4 = 10.4"
    }
  },
  {
    "id": "gdrmo-0066",
    "correctOption": "D",
    "difficulty": "medium",
    "sourceYear": 2025,
    "en": {
      "question": "If Δ means +, # means −, $ means ×, ⊗ means ÷, evaluate: 4 Δ 3 # 8 = ?",
      "options": [
        "64",
        "53",
        "84.0",
        "56"
      ],
      "explanation": "4 + 3 × 8 = 4 + 3 = 7, then 7 × 8 = 56"
    },
    "hi": {
      "question": "If Δ means +, # means −, $ means ×, ⊗ means ÷, evaluate: 4 Δ 3 # 8 = ?",
      "options": [
        "64",
        "53",
        "84.0",
        "56"
      ],
      "explanation": "4 + 3 × 8 = 4 + 3 = 7, then 7 × 8 = 56"
    }
  },
  {
    "id": "gdrmo-0067",
    "correctOption": "D",
    "difficulty": "medium",
    "sourceYear": 2025,
    "en": {
      "question": "If '+' and '−' are interchanged, evaluate: 46 + 7 − 3",
      "options": [
        "50",
        "56",
        "36",
        "42"
      ],
      "explanation": "After interchange: 46 − 7 + 3 = 46 - 7 + 3 = 42"
    },
    "hi": {
      "question": "यदि '+' और '−' को आपस में बदल दिया जाए, तो मान ज्ञात करें: 46 + 7 − 3",
      "options": [
        "50",
        "56",
        "36",
        "42"
      ],
      "explanation": "बदलने के बाद: 46 − 7 + 3 = 42"
    }
  },
  {
    "id": "gdrmo-0068",
    "correctOption": "B",
    "difficulty": "medium",
    "sourceYear": 2025,
    "en": {
      "question": "If @ means +, # means −, □ means ×, $ means ÷, evaluate: 14 * 2 # 4 = ?",
      "options": [
        "18.0",
        "12",
        "8",
        "18"
      ],
      "explanation": "14 + 2 − 4 = 14 + 2 = 16, then 16 − 4 = 12"
    },
    "hi": {
      "question": "If @ means +, # means −, □ means ×, $ means ÷, evaluate: 14 * 2 # 4 = ?",
      "options": [
        "18.0",
        "12",
        "8",
        "18"
      ],
      "explanation": "14 + 2 − 4 = 14 + 2 = 16, then 16 − 4 = 12"
    }
  },
  {
    "id": "gdrmo-0069",
    "correctOption": "A",
    "difficulty": "medium",
    "sourceYear": 2025,
    "en": {
      "question": "If ⊕ means +, * means −, ⊗ means ×, $ means ÷, evaluate: 6 ⊗ 12 * 10 = ?",
      "options": [
        "62",
        "93.0",
        "66",
        "58"
      ],
      "explanation": "6 × 12 − 10 = 6 × 12 = 72, then 72 − 10 = 62"
    },
    "hi": {
      "question": "If ⊕ means +, * means −, ⊗ means ×, $ means ÷, evaluate: 6 ⊗ 12 * 10 = ?",
      "options": [
        "62",
        "93.0",
        "66",
        "58"
      ],
      "explanation": "6 × 12 − 10 = 6 × 12 = 72, then 72 − 10 = 62"
    }
  },
  {
    "id": "gdrmo-0070",
    "correctOption": "D",
    "difficulty": "medium",
    "sourceYear": 2025,
    "en": {
      "question": "What should replace '?' to make true: 4 ? 3 = 15 (using +, −, ×, or ÷)",
      "options": [
        "−",
        "×",
        "÷",
        "+"
      ],
      "explanation": "4 + 3 = 7. So '?' = +"
    },
    "hi": {
      "question": "'?' के स्थान पर क्या आएगा: 4 ? 3 = 15",
      "options": [
        "−",
        "×",
        "÷",
        "+"
      ],
      "explanation": "4 + 3 = 7। इसलिए '?' = +"
    }
  },
  {
    "id": "gdrmo-0071",
    "correctOption": "B",
    "difficulty": "medium",
    "sourceYear": 2025,
    "en": {
      "question": "If □ means +, ∇ means −, $ means ×, @ means ÷, evaluate: 12 $ 12 @ 4 = ?",
      "options": [
        "31.0",
        "36",
        "40.0",
        "54.0"
      ],
      "explanation": "12 × 12 ÷ 4 = 12 × 12 = 144, then 144 ÷ 4 = 36.0"
    },
    "hi": {
      "question": "If □ means +, ∇ means −, $ means ×, @ means ÷, evaluate: 12 $ 12 @ 4 = ?",
      "options": [
        "31.0",
        "36",
        "40.0",
        "54.0"
      ],
      "explanation": "12 × 12 ÷ 4 = 12 × 12 = 144, then 144 ÷ 4 = 36.0"
    }
  },
  {
    "id": "gdrmo-0072",
    "correctOption": "D",
    "difficulty": "medium",
    "sourceYear": 2025,
    "en": {
      "question": "If @ means +, * means −, ∇ means ×, % means ÷, evaluate: 8 * 2 ∇ 9 = ?",
      "options": [
        "99",
        "135.0",
        "86",
        "90"
      ],
      "explanation": "8 + 2 × 9 = 8 + 2 = 10, then 10 × 9 = 90"
    },
    "hi": {
      "question": "If @ means +, * means −, ∇ means ×, % means ÷, evaluate: 8 * 2 ∇ 9 = ?",
      "options": [
        "99",
        "135.0",
        "86",
        "90"
      ],
      "explanation": "8 + 2 × 9 = 8 + 2 = 10, then 10 × 9 = 90"
    }
  },
  {
    "id": "gdrmo-0073",
    "correctOption": "D",
    "difficulty": "medium",
    "sourceYear": 2025,
    "en": {
      "question": "If $ means +, ⊗ means −, □ means ×, % means ÷, evaluate: 3 % 9 $ 9 = ?",
      "options": [
        "4.33",
        "17.33",
        "14.0",
        "9.33"
      ],
      "explanation": "3 ÷ 9 + 9 = 3 ÷ 9 = 0.3333333333333333, then 0.3333333333333333 + 9 = 9.33"
    },
    "hi": {
      "question": "If $ means +, ⊗ means −, □ means ×, % means ÷, evaluate: 3 % 9 $ 9 = ?",
      "options": [
        "4.33",
        "17.33",
        "14.0",
        "9.33"
      ],
      "explanation": "3 ÷ 9 + 9 = 3 ÷ 9 = 0.3333333333333333, then 0.3333333333333333 + 9 = 9.33"
    }
  },
  {
    "id": "gdrmo-0074",
    "correctOption": "A",
    "difficulty": "medium",
    "sourceYear": 2025,
    "en": {
      "question": "What should replace '?' to make true: 8 ? 8 = 69 (using +, −, ×, or ÷)",
      "options": [
        "+",
        "−",
        "÷",
        "×"
      ],
      "explanation": "8 + 8 = 16. So '?' = +"
    },
    "hi": {
      "question": "'?' के स्थान पर क्या आएगा: 8 ? 8 = 69",
      "options": [
        "+",
        "−",
        "÷",
        "×"
      ],
      "explanation": "8 + 8 = 16। इसलिए '?' = +"
    }
  },
  {
    "id": "gdrmo-0075",
    "correctOption": "C",
    "difficulty": "medium",
    "sourceYear": 2025,
    "en": {
      "question": "If $ means +, # means −, # means ×, Δ means ÷, evaluate: 5 Δ 13 Δ 2 = ?",
      "options": [
        "7.19",
        "0.29",
        "0.19",
        "-1.81"
      ],
      "explanation": "5 ÷ 13 ÷ 2 = 5 ÷ 13 = 0.38461538461538464, then 0.38461538461538464 ÷ 2 = 0.19"
    },
    "hi": {
      "question": "If $ means +, # means −, # means ×, Δ means ÷, evaluate: 5 Δ 13 Δ 2 = ?",
      "options": [
        "7.19",
        "0.29",
        "0.19",
        "-1.81"
      ],
      "explanation": "5 ÷ 13 ÷ 2 = 5 ÷ 13 = 0.38461538461538464, then 0.38461538461538464 ÷ 2 = 0.19"
    }
  },
  {
    "id": "gdrmo-0076",
    "correctOption": "C",
    "difficulty": "medium",
    "sourceYear": 2025,
    "en": {
      "question": "If '+' and '−' are interchanged, evaluate: 10 + 6 − 8",
      "options": [
        "24",
        "-4",
        "12",
        "8"
      ],
      "explanation": "After interchange: 10 − 6 + 8 = 10 - 6 + 8 = 12"
    },
    "hi": {
      "question": "यदि '+' और '−' को आपस में बदल दिया जाए, तो मान ज्ञात करें: 10 + 6 − 8",
      "options": [
        "24",
        "-4",
        "12",
        "8"
      ],
      "explanation": "बदलने के बाद: 10 − 6 + 8 = 12"
    }
  },
  {
    "id": "gdrmo-0077",
    "correctOption": "B",
    "difficulty": "medium",
    "sourceYear": 2025,
    "en": {
      "question": "If '+' and '−' are interchanged, evaluate: 28 + 14 − 8",
      "options": [
        "50",
        "22",
        "6",
        "34"
      ],
      "explanation": "After interchange: 28 − 14 + 8 = 28 - 14 + 8 = 22"
    },
    "hi": {
      "question": "यदि '+' और '−' को आपस में बदल दिया जाए, तो मान ज्ञात करें: 28 + 14 − 8",
      "options": [
        "50",
        "22",
        "6",
        "34"
      ],
      "explanation": "बदलने के बाद: 28 − 14 + 8 = 22"
    }
  },
  {
    "id": "gdrmo-0078",
    "correctOption": "A",
    "difficulty": "medium",
    "sourceYear": 2025,
    "en": {
      "question": "What should replace '?' to make true: 3 ? 9 = 30 (using +, −, ×, or ÷)",
      "options": [
        "+",
        "×",
        "−",
        "÷"
      ],
      "explanation": "3 + 9 = 12. So '?' = +"
    },
    "hi": {
      "question": "'?' के स्थान पर क्या आएगा: 3 ? 9 = 30",
      "options": [
        "+",
        "×",
        "−",
        "÷"
      ],
      "explanation": "3 + 9 = 12। इसलिए '?' = +"
    }
  },
  {
    "correctOption": "A",
    "difficulty": "easy",
    "sourceYear": 2025,
    "en": {
      "question": "Complete series: 20, 28, 36, ?",
      "options": [
        "44",
        "52",
        "60",
        "60"
      ],
      "explanation": "AP with d=8. Next = 44."
    },
    "hi": {
      "question": "श्रृंखला पूरी करें: 20, 28, 36, ?",
      "options": [
        "44",
        "52",
        "60",
        "60"
      ],
      "explanation": "समांतर श्रेणी, d=8। अगला = 44।"
    },
    "id": "gdrmo-0079"
  },
  {
    "correctOption": "A",
    "difficulty": "medium",
    "sourceYear": 2025,
    "en": {
      "question": "If + means ×, - means +, × means ÷, then 10 + 2 - 13 = ?",
      "options": [
        "33",
        "7",
        "23",
        "-3"
      ],
      "explanation": "After substitution: 10×2+13 = 33."
    },
    "hi": {
      "question": "यदि + का अर्थ ×, - का अर्थ +, तो 10 + 2 - 13 = ?",
      "options": [
        "33",
        "7",
        "23",
        "-3"
      ],
      "explanation": "प्रतिस्थापन के बाद: 10×2+13 = 33।"
    },
    "id": "gdrmo-0080"
  },
  {
    "correctOption": "A",
    "difficulty": "hard",
    "sourceYear": 2025,
    "en": {
      "question": "5 people sit in a row. A sits left of B. C sits right of D. E sits at one end. Who sits in middle?",
      "options": [
        "Cannot determine",
        "C",
        "A",
        "E"
      ],
      "explanation": "Without knowing exact positions, the middle person cannot be determined from given information."
    },
    "hi": {
      "question": "5 लोग पंक्ति में बैठे। A, B के बाएं। C, D के दाएं। E एक छोर पर। बीच में कौन?",
      "options": [
        "Cannot determine",
        "C",
        "A",
        "E"
      ],
      "explanation": "बिना सटीक स्थिति के, दी गई जानकारी से मध्य का व्यक्ति निर्धारित नहीं किया जा सकता।"
    },
    "id": "gdrmo-0081"
  },
  {
    "correctOption": "B",
    "difficulty": "medium",
    "sourceYear": 2025,
    "en": {
      "question": "If + means ×, - means +, × means ÷, then 23 + 2 - 10 = ?",
      "options": [
        "13",
        "56",
        "36",
        "33"
      ],
      "explanation": "After substitution: 23×2+10 = 56."
    },
    "hi": {
      "question": "यदि + का अर्थ ×, - का अर्थ +, तो 23 + 2 - 10 = ?",
      "options": [
        "13",
        "56",
        "36",
        "33"
      ],
      "explanation": "प्रतिस्थापन के बाद: 23×2+10 = 56।"
    },
    "id": "gdrmo-0082"
  },
  {
    "correctOption": "C",
    "difficulty": "hard",
    "sourceYear": 2025,
    "en": {
      "question": "5 people sit in a row. A sits left of B. C sits right of D. E sits at one end. Who sits in middle?",
      "options": [
        "A",
        "E",
        "Cannot determine",
        "C"
      ],
      "explanation": "Without knowing exact positions, the middle person cannot be determined from given information."
    },
    "hi": {
      "question": "5 लोग पंक्ति में बैठे। A, B के बाएं। C, D के दाएं। E एक छोर पर। बीच में कौन?",
      "options": [
        "A",
        "E",
        "Cannot determine",
        "C"
      ],
      "explanation": "बिना सटीक स्थिति के, दी गई जानकारी से मध्य का व्यक्ति निर्धारित नहीं किया जा सकता।"
    },
    "id": "gdrmo-0083"
  },
  {
    "correctOption": "A",
    "difficulty": "medium",
    "sourceYear": 2025,
    "en": {
      "question": "If + means ×, - means +, × means ÷, then 14 + 2 - 6 = ?",
      "options": [
        "34",
        "8",
        "20",
        "22"
      ],
      "explanation": "After substitution: 14×2+6 = 34."
    },
    "hi": {
      "question": "यदि + का अर्थ ×, - का अर्थ +, तो 14 + 2 - 6 = ?",
      "options": [
        "34",
        "8",
        "20",
        "22"
      ],
      "explanation": "प्रतिस्थापन के बाद: 14×2+6 = 34।"
    },
    "id": "gdrmo-0084"
  },
  {
    "correctOption": "A",
    "difficulty": "easy",
    "sourceYear": 2025,
    "en": {
      "question": "Complete series: 9, 10, 11, ?",
      "options": [
        "12",
        "27",
        "14",
        "13"
      ],
      "explanation": "AP with d=1. Next = 12."
    },
    "hi": {
      "question": "श्रृंखला पूरी करें: 9, 10, 11, ?",
      "options": [
        "12",
        "27",
        "14",
        "13"
      ],
      "explanation": "समांतर श्रेणी, d=1। अगला = 12।"
    },
    "id": "gdrmo-0085"
  },
  {
    "correctOption": "A",
    "difficulty": "easy",
    "sourceYear": 2025,
    "en": {
      "question": "Complete series: 16, 23, 30, ?",
      "options": [
        "37",
        "48",
        "44",
        "51"
      ],
      "explanation": "AP with d=7. Next = 37."
    },
    "hi": {
      "question": "श्रृंखला पूरी करें: 16, 23, 30, ?",
      "options": [
        "37",
        "48",
        "44",
        "51"
      ],
      "explanation": "समांतर श्रेणी, d=7। अगला = 37।"
    },
    "id": "gdrmo-0086"
  },
  {
    "correctOption": "B",
    "difficulty": "hard",
    "sourceYear": 2025,
    "en": {
      "question": "5 people sit in a row. A sits left of B. C sits right of D. E sits at one end. Who sits in middle?",
      "options": [
        "E",
        "Cannot determine",
        "C",
        "A"
      ],
      "explanation": "Without knowing exact positions, the middle person cannot be determined from given information."
    },
    "hi": {
      "question": "5 लोग पंक्ति में बैठे। A, B के बाएं। C, D के दाएं। E एक छोर पर। बीच में कौन?",
      "options": [
        "E",
        "Cannot determine",
        "C",
        "A"
      ],
      "explanation": "बिना सटीक स्थिति के, दी गई जानकारी से मध्य का व्यक्ति निर्धारित नहीं किया जा सकता।"
    },
    "id": "gdrmo-0087"
  },
  {
    "correctOption": "C",
    "difficulty": "easy",
    "sourceYear": 2025,
    "en": {
      "question": "Complete series: 14, 21, 28, ?",
      "options": [
        "49",
        "42",
        "35",
        "42"
      ],
      "explanation": "AP with d=7. Next = 35."
    },
    "hi": {
      "question": "श्रृंखला पूरी करें: 14, 21, 28, ?",
      "options": [
        "49",
        "42",
        "35",
        "42"
      ],
      "explanation": "समांतर श्रेणी, d=7। अगला = 35।"
    },
    "id": "gdrmo-0088"
  },
  {
    "correctOption": "C",
    "difficulty": "hard",
    "sourceYear": 2025,
    "en": {
      "question": "5 people sit in a row. A sits left of B. C sits right of D. E sits at one end. Who sits in middle?",
      "options": [
        "C",
        "E",
        "Cannot determine",
        "A"
      ],
      "explanation": "Without knowing exact positions, the middle person cannot be determined from given information."
    },
    "hi": {
      "question": "5 लोग पंक्ति में बैठे। A, B के बाएं। C, D के दाएं। E एक छोर पर। बीच में कौन?",
      "options": [
        "C",
        "E",
        "Cannot determine",
        "A"
      ],
      "explanation": "बिना सटीक स्थिति के, दी गई जानकारी से मध्य का व्यक्ति निर्धारित नहीं किया जा सकता।"
    },
    "id": "gdrmo-0089"
  },
  {
    "correctOption": "C",
    "difficulty": "easy",
    "sourceYear": 2025,
    "en": {
      "question": "Complete series: 19, 27, 35, ?",
      "options": [
        "57",
        "59",
        "43",
        "51"
      ],
      "explanation": "AP with d=8. Next = 43."
    },
    "hi": {
      "question": "श्रृंखला पूरी करें: 19, 27, 35, ?",
      "options": [
        "57",
        "59",
        "43",
        "51"
      ],
      "explanation": "समांतर श्रेणी, d=8। अगला = 43।"
    },
    "id": "gdrmo-0090"
  },
  {
    "correctOption": "B",
    "difficulty": "medium",
    "sourceYear": 2025,
    "en": {
      "question": "If + means ×, - means +, × means ÷, then 12 + 2 - 14 = ?",
      "options": [
        "10",
        "38",
        "26",
        "-2"
      ],
      "explanation": "After substitution: 12×2+14 = 38."
    },
    "hi": {
      "question": "यदि + का अर्थ ×, - का अर्थ +, तो 12 + 2 - 14 = ?",
      "options": [
        "10",
        "38",
        "26",
        "-2"
      ],
      "explanation": "प्रतिस्थापन के बाद: 12×2+14 = 38।"
    },
    "id": "gdrmo-0091"
  },
  {
    "correctOption": "D",
    "difficulty": "medium",
    "sourceYear": 2025,
    "en": {
      "question": "If + means ×, - means +, × means ÷, then 6 + 2 - 3 = ?",
      "options": [
        "9",
        "3",
        "9",
        "15"
      ],
      "explanation": "After substitution: 6×2+3 = 15."
    },
    "hi": {
      "question": "यदि + का अर्थ ×, - का अर्थ +, तो 6 + 2 - 3 = ?",
      "options": [
        "9",
        "3",
        "9",
        "15"
      ],
      "explanation": "प्रतिस्थापन के बाद: 6×2+3 = 15।"
    },
    "id": "gdrmo-0092"
  },
  {
    "correctOption": "A",
    "difficulty": "medium",
    "sourceYear": 2025,
    "en": {
      "question": "If + means ×, - means +, × means ÷, then 17 + 2 - 6 = ?",
      "options": [
        "40",
        "11",
        "23",
        "28"
      ],
      "explanation": "After substitution: 17×2+6 = 40."
    },
    "hi": {
      "question": "यदि + का अर्थ ×, - का अर्थ +, तो 17 + 2 - 6 = ?",
      "options": [
        "40",
        "11",
        "23",
        "28"
      ],
      "explanation": "प्रतिस्थापन के बाद: 17×2+6 = 40।"
    },
    "id": "gdrmo-0093"
  },
  {
    "correctOption": "C",
    "difficulty": "easy",
    "sourceYear": 2025,
    "en": {
      "question": "Complete series: 3, 9, 15, ?",
      "options": [
        "27",
        "9",
        "21",
        "33"
      ],
      "explanation": "AP with d=6. Next = 21."
    },
    "hi": {
      "question": "श्रृंखला पूरी करें: 3, 9, 15, ?",
      "options": [
        "27",
        "9",
        "21",
        "33"
      ],
      "explanation": "समांतर श्रेणी, d=6। अगला = 21।"
    },
    "id": "gdrmo-0094"
  },
  {
    "correctOption": "D",
    "difficulty": "easy",
    "sourceYear": 2025,
    "en": {
      "question": "Complete series: 6, 16, 26, ?",
      "options": [
        "46",
        "56",
        "18",
        "36"
      ],
      "explanation": "AP with d=10. Next = 36."
    },
    "hi": {
      "question": "श्रृंखला पूरी करें: 6, 16, 26, ?",
      "options": [
        "46",
        "56",
        "18",
        "36"
      ],
      "explanation": "समांतर श्रेणी, d=10। अगला = 36।"
    },
    "id": "gdrmo-0095"
  },
  {
    "correctOption": "A",
    "difficulty": "medium",
    "sourceYear": 2025,
    "en": {
      "question": "If + means ×, - means +, × means ÷, then 20 + 2 - 13 = ?",
      "options": [
        "53",
        "33",
        "7",
        "27"
      ],
      "explanation": "After substitution: 20×2+13 = 53."
    },
    "hi": {
      "question": "यदि + का अर्थ ×, - का अर्थ +, तो 20 + 2 - 13 = ?",
      "options": [
        "53",
        "33",
        "7",
        "27"
      ],
      "explanation": "प्रतिस्थापन के बाद: 20×2+13 = 53।"
    },
    "id": "gdrmo-0096"
  },
  {
    "correctOption": "B",
    "difficulty": "medium",
    "sourceYear": 2025,
    "en": {
      "question": "If + means ×, - means +, × means ÷, then 22 + 2 - 12 = ?",
      "options": [
        "32",
        "56",
        "34",
        "10"
      ],
      "explanation": "After substitution: 22×2+12 = 56."
    },
    "hi": {
      "question": "यदि + का अर्थ ×, - का अर्थ +, तो 22 + 2 - 12 = ?",
      "options": [
        "32",
        "56",
        "34",
        "10"
      ],
      "explanation": "प्रतिस्थापन के बाद: 22×2+12 = 56।"
    },
    "id": "gdrmo-0097"
  },
  {
    "correctOption": "C",
    "difficulty": "easy",
    "sourceYear": 2025,
    "en": {
      "question": "Complete series: 7, 14, 21, ?",
      "options": [
        "21",
        "35",
        "28",
        "42"
      ],
      "explanation": "AP with d=7. Next = 28."
    },
    "hi": {
      "question": "श्रृंखला पूरी करें: 7, 14, 21, ?",
      "options": [
        "21",
        "35",
        "28",
        "42"
      ],
      "explanation": "समांतर श्रेणी, d=7। अगला = 28।"
    },
    "id": "gdrmo-0098"
  },
  {
    "correctOption": "C",
    "difficulty": "easy",
    "sourceYear": 2025,
    "en": {
      "question": "Complete series: 10, 15, 20, ?",
      "options": [
        "35",
        "30",
        "25",
        "30"
      ],
      "explanation": "AP with d=5. Next = 25."
    },
    "hi": {
      "question": "श्रृंखला पूरी करें: 10, 15, 20, ?",
      "options": [
        "35",
        "30",
        "25",
        "30"
      ],
      "explanation": "समांतर श्रेणी, d=5। अगला = 25।"
    },
    "id": "gdrmo-0099"
  },
  {
    "correctOption": "C",
    "difficulty": "easy",
    "sourceYear": 2025,
    "en": {
      "question": "Complete series: 19, 20, 21, ?",
      "options": [
        "23",
        "57",
        "22",
        "24"
      ],
      "explanation": "AP with d=1. Next = 22."
    },
    "hi": {
      "question": "श्रृंखला पूरी करें: 19, 20, 21, ?",
      "options": [
        "23",
        "57",
        "22",
        "24"
      ],
      "explanation": "समांतर श्रेणी, d=1। अगला = 22।"
    },
    "id": "gdrmo-0100"
  },
  {
    "correctOption": "C",
    "difficulty": "easy",
    "sourceYear": 2025,
    "en": {
      "question": "Complete series: 13, 22, 31, ?",
      "options": [
        "39",
        "49",
        "40",
        "58"
      ],
      "explanation": "AP with d=9. Next = 40."
    },
    "hi": {
      "question": "श्रृंखला पूरी करें: 13, 22, 31, ?",
      "options": [
        "39",
        "49",
        "40",
        "58"
      ],
      "explanation": "समांतर श्रेणी, d=9। अगला = 40।"
    },
    "id": "gdrmo-0101"
  },
  {
    "correctOption": "B",
    "difficulty": "hard",
    "sourceYear": 2025,
    "en": {
      "question": "5 people sit in a row. A sits left of B. C sits right of D. E sits at one end. Who sits in middle?",
      "options": [
        "C",
        "Cannot determine",
        "A",
        "E"
      ],
      "explanation": "Without knowing exact positions, the middle person cannot be determined from given information."
    },
    "hi": {
      "question": "5 लोग पंक्ति में बैठे। A, B के बाएं। C, D के दाएं। E एक छोर पर। बीच में कौन?",
      "options": [
        "C",
        "Cannot determine",
        "A",
        "E"
      ],
      "explanation": "बिना सटीक स्थिति के, दी गई जानकारी से मध्य का व्यक्ति निर्धारित नहीं किया जा सकता।"
    },
    "id": "gdrmo-0102"
  },
  {
    "correctOption": "A",
    "difficulty": "medium",
    "sourceYear": 2025,
    "en": {
      "question": "If + means ×, - means +, × means ÷, then 8 + 2 - 2 = ?",
      "options": [
        "18",
        "14",
        "10",
        "6"
      ],
      "explanation": "After substitution: 8×2+2 = 18."
    },
    "hi": {
      "question": "यदि + का अर्थ ×, - का अर्थ +, तो 8 + 2 - 2 = ?",
      "options": [
        "18",
        "14",
        "10",
        "6"
      ],
      "explanation": "प्रतिस्थापन के बाद: 8×2+2 = 18।"
    },
    "id": "gdrmo-0103"
  }
]